crossref/__init__.py
crossref/restful.py
crossref/utils.py
crossref/validators.py
crossrefapi-1.7.0.dist-info/LICENSE
crossrefapi-1.7.0.dist-info/METADATA
crossrefapi-1.7.0.dist-info/WHEEL
crossrefapi-1.7.0.dist-info/RECORD
