Metadata-Version: 2.3
Name: crossrefapi
Version: 1.7.0
Summary: Library that implements the endpoints of the Crossref API
Author: Fabio Batalha
Author-email: fabio.batalha@erudit.org
Requires-Python: >=3.10,<4.0
Classifier: Programming Language :: Python :: 3
Classifier: Programming Language :: Python :: 3.10
Classifier: Programming Language :: Python :: 3.11
Classifier: Programming Language :: Python :: 3.12
Classifier: Programming Language :: Python :: 3.13
Requires-Dist: ipython (>=8.28.0,<9.0.0)
Requires-Dist: requests (>=2.32.3,<3.0.0)
Requires-Dist: urllib3 (>=2.2.3,<3.0.0)
